dodfminer/__init__.py
dodfminer/__version__.py
dodfminer/cli.py
dodfminer/run.py
dodfminer/downloader/__init__.py
dodfminer/downloader/core.py
dodfminer/downloader/helper.py
dodfminer/extract/__init__.py
dodfminer/extract/polished/__init__.py
dodfminer/extract/polished/core.py
dodfminer/extract/polished/create_xml.py
dodfminer/extract/polished/helper.py
dodfminer/extract/polished/acts/__init__.py
dodfminer/extract/polished/acts/abono.py
dodfminer/extract/polished/acts/aditamento.py
dodfminer/extract/polished/acts/anulacao_revogacao.py
dodfminer/extract/polished/acts/aposentadoria.py
dodfminer/extract/polished/acts/base.py
dodfminer/extract/polished/acts/base_contratos.py
dodfminer/extract/polished/acts/cessoes.py
dodfminer/extract/polished/acts/contrato.py
dodfminer/extract/polished/acts/contrato2.py
dodfminer/extract/polished/acts/contrato_convenio.py
dodfminer/extract/polished/acts/convenio.py
dodfminer/extract/polished/acts/exoneracao.py
dodfminer/extract/polished/acts/licitacao.py
dodfminer/extract/polished/acts/nomeacao.py
dodfminer/extract/polished/acts/retificacao.py
dodfminer/extract/polished/acts/reversoes.py
dodfminer/extract/polished/acts/sem_efeito_aposentadoria.py
dodfminer/extract/polished/acts/sem_efeito_exo_nom.py
dodfminer/extract/polished/acts/substituicao.py
dodfminer/extract/polished/acts/suspensao.py
dodfminer/extract/polished/acts/models/abono.pkl
dodfminer/extract/polished/acts/models/aposentadoria.pkl
dodfminer/extract/polished/acts/models/cessao.pkl
dodfminer/extract/polished/acts/models/comissionados_exo.pkl
dodfminer/extract/polished/acts/models/comissionados_nome.pkl
dodfminer/extract/polished/acts/models/comissionados_ret.pkl
dodfminer/extract/polished/acts/models/contratos_lbfgs.pkl
dodfminer/extract/polished/acts/models/efetivos_exo.pkl
dodfminer/extract/polished/acts/models/efetivos_nome.pkl
dodfminer/extract/polished/acts/models/efetivos_ret.pkl
dodfminer/extract/polished/acts/models/modelo_aditamento_contratual.pkl
dodfminer-1.4.8.dist-info/LICENSE
dodfminer-1.4.8.dist-info/METADATA
dodfminer-1.4.8.dist-info/WHEEL
dodfminer-1.4.8.dist-info/entry_points.txt
dodfminer-1.4.8.dist-info/top_level.txt
dodfminer-1.4.8.dist-info/RECORD
