Metadata-Version: 2.1
Name: dodfminer
Version: 1.4.8
Summary: UNKNOWN
Home-page: https://github.com/UnB-KnEDLe/DODFMiner
Author: KnEDLe
Author-email: author@example.com
License: UNKNOWN
Platform: UNKNOWN
Classifier: Programming Language :: Python :: 3
Classifier: License :: OSI Approved :: MIT License
Classifier: Operating System :: OS Independent
Requires-Python: >=3.6
Requires-Dist: PyMuPDF (==1.21.1)
Requires-Dist: beautifulsoup4 (==4.12.0)
Requires-Dist: certifi (==2022.12.7)
Requires-Dist: chardet (==5.1.0)
Requires-Dist: coveralls (==3.3.1)
Requires-Dist: idna (==3.4)
Requires-Dist: joblib (==1.2.0)
Requires-Dist: lxml (==4.9.2)
Requires-Dist: nltk (==3.8.1)
Requires-Dist: numpy (==1.24.2)
Requires-Dist: pandas (==1.5.3)
Requires-Dist: pylint (==2.17.1)
Requires-Dist: pytest-cov (==4.0.0)
Requires-Dist: pytest-mock (==3.10.0)
Requires-Dist: pytest (==7.2.2)
Requires-Dist: python-dateutil (==2.8.1)
Requires-Dist: pytz (==2023.3)
Requires-Dist: requests-mock (==1.10.0)
Requires-Dist: requests (==2.28.2)
Requires-Dist: scikit-learn (==1.2.2)
Requires-Dist: sklearn-crfsuite (==0.3.6)
Requires-Dist: tqdm (==4.65.0)
